README.txt
setup.cfg
setup.py
docs/HISTORY.txt
docs/INSTALL.txt
docs/LICENSE.GPL
docs/LICENSE.txt
quintagroup/__init__.py
quintagroup.pingtool.egg-info/PKG-INFO
quintagroup.pingtool.egg-info/SOURCES.txt
quintagroup.pingtool.egg-info/dependency_links.txt
quintagroup.pingtool.egg-info/entry_points.txt
quintagroup.pingtool.egg-info/namespace_packages.txt
quintagroup.pingtool.egg-info/not-zip-safe
quintagroup.pingtool.egg-info/requires.txt
quintagroup.pingtool.egg-info/top_level.txt
quintagroup/pingtool/PingInfo.py
quintagroup/pingtool/PingTool.py
quintagroup/pingtool/__init__.py
quintagroup/pingtool/canonicalUrl.py
quintagroup/pingtool/config.py
quintagroup/pingtool/configure.zcml
quintagroup/pingtool/extender.py
quintagroup/pingtool/interfaces.py
quintagroup/pingtool/profiles.zcml
quintagroup/pingtool/setuphandlers.py
quintagroup/pingtool/subscribers.py
quintagroup/pingtool/tool.gif
quintagroup/pingtool/utils.py
quintagroup/pingtool/version.txt
quintagroup/pingtool/Extensions/Install.py
quintagroup/pingtool/browser/__init__.py
quintagroup/pingtool/browser/configure.zcml
quintagroup/pingtool/browser/ping.py
quintagroup/pingtool/browser/return_ping.pt
quintagroup/pingtool/locales/quintagroup.pingtool.pot
quintagroup/pingtool/locales/uk/LC_MESSAGES/quintagroup.pingtool.po
quintagroup/pingtool/profiles/default/actionicons.xml
quintagroup/pingtool/profiles/default/actions.xml
quintagroup/pingtool/profiles/default/componentregistry.xml
quintagroup/pingtool/profiles/default/controlpanel.xml
quintagroup/pingtool/profiles/default/import_steps.xml
quintagroup/pingtool/profiles/default/metadata.xml
quintagroup/pingtool/profiles/default/propertiestool.xml
quintagroup/pingtool/profiles/default/quintagroup.pingtool_various.txt
quintagroup/pingtool/profiles/default/toolset.xml
quintagroup/pingtool/profiles/default/types.xml
quintagroup/pingtool/profiles/default/types/PingInfo.xml
quintagroup/pingtool/profiles/default/types/PingTool.xml
quintagroup/pingtool/profiles/uninstall/componentregistry.xml
quintagroup/pingtool/profiles/uninstall/import_steps.xml
quintagroup/pingtool/profiles/uninstall/quintagroup.pingtool-uninstall.txt
quintagroup/pingtool/tests/__init__.py
quintagroup/pingtool/tests/base.py
quintagroup/pingtool/tests/browser.txt
quintagroup/pingtool/tests/config.py
quintagroup/pingtool/tests/testPropertiesToolConf.py
