Metadata-Version: 1.0
Name: quintagroup.pingtool
Version: 1.1.3
Summary: quintagroup.pingtool is a simple tool to enable pinging of external feed agregators for Plone 3.1.x
Home-page: http://quintagroup.com/services/plone-development/products/ping-tool
Author: liebster
Author-email: support@quintagroup.com
License: GPL
Platform: UNKNOWN
Classifier: Framework :: Plone
Classifier: Programming Language :: Python
Classifier: Topic :: Software Development :: Libraries :: Python Modules
